SEM 3/DSDL/LAB8/Q5/q.v
module encoder16to4(i,f);
input [15:0]i;
output reg [4:0]f;
integer j;
always @ (i)
begin
	for(j=0;j<16;j=j+1)
	begin
		if(i[j])
			f=j;
	end
end
endmodule

SEM 3/DSDL/LAB8/Q5/q_tb.v
`timescale 1ns/1ns
`include "q.v"
module q_tb();
reg [15:0]i;
wire [4:0]f;
integer j;
encoder16to4 f1(i,f);
initial
begin
$dumpfile("q_tb.vcd");
$dumpvars(0,q_tb);

for(j=0;j<16;j=j+1)
begin
i=0;
i[j]=1; #20;
end

$display("Test Complete");
end
endmodule

SEM 3/DSDL/LAB8/Q5/q_tb.vcd
$date
	Thu Oct 20 11:09:48 2022
$end
$version
	Icarus Verilog
$end
$timescale
	1ns
$end
$scope module q_tb $end
$var wire 5 ! f [4:0] $end
$var reg 16 " i [15:0] $end
$var integer 32 # j [31:0] $end
$scope module f1 $end
$var wire 16 $ i [15:0] $end
$var reg 5 % f [4:0] $end
$var integer 32 & j [31:0] $end
$upscope $end
$upscope $end
$enddefinitions $end
#0
$dumpvars
b10000 &
b0 %
b1 $
b0 #
b1 "
b0 !
$end
#20
b1 !
b1 %
b10000 &
b10 "
b10 $
b1 #
#40
b10 !
b10 %
b10000 &
b100 "
b100 $
b10 #
#60
b11 !
b11 %
b10000 &
b1000 "
b1000 $
b11 #
#80
b100 !
b100 %
b10000 &
b10000 "
b10000 $
b100 #
#100
b101 !
b101 %
b10000 &
b100000 "
b100000 $
b101 #
#120
b110 !
b110 %
b10000 &
b1000000 "
b1000000 $
b110 #
#140
b111 !
b111 %
b10000 &
b10000000 "
b10000000 $
b111 #
#160
b1000 !
b1000 %
b10000 &
b100000000 "
b100000000 $
b1000 #
#180
b1001 !
b1001 %
b10000 &
b1000000000 "
b1000000000 $
b1001 #
#200
b1010 !
b1010 %
b10000 &
b10000000000 "
b10000000000 $
b1010 #
#220
b1011 !
b1011 %
b10000 &
b100000000000 "
b100000000000 $
b1011 #
#240
b1100 !
b1100 %
b10000 &
b1000000000000 "
b1000000000000 $
b1100 #
#260
b1101 !
b1101 %
b10000 &
b10000000000000 "
b10000000000000 $
b1101 #
#280
b1110 !
b1110 %
b10000 &
b100000000000000 "
b100000000000000 $
b1110 #
#300
b1111 !
b1111 %
b10000 &
b1000000000000000 "
b1000000000000000 $
b1111 #
#320
b10000 #
