SEM 3/DSDL/LAB2/Q2/Q2A/q2a.v
module q2a(A,B,C,D,f);
input A,B,C,D;
output f;
assign f=(~B|D)&(B|C);
endmodule

SEM 3/DSDL/LAB2/Q2/Q2A/q2a_tb.v
`timescale 1ns/1ns
`include "q2a.v"

module q2a_tb();
reg A,B,C,D;
wire f;

q2a q2a(A,B,C,D,f);
initial
begin

$dumpfile("q2a_tb.vcd");
$dumpvars(0,q2a_tb);

A=1'b0; B=1'b0; C=1'b0; D=1'b0; #20;
A=1'b0; B=1'b0; C=1'b0; D=1'b1; #20;
A=1'b0; B=1'b0; C=1'b1; D=1'b0; #20;
A=1'b0; B=1'b0; C=1'b1; D=1'b1; #20;
A=1'b0; B=1'b1; C=1'b0; D=1'b0; #20;
A=1'b0; B=1'b1; C=1'b0; D=1'b1; #20;
A=1'b0; B=1'b1; C=1'b1; D=1'b0; #20;
A=1'b0; B=1'b1; C=1'b1; D=1'b1; #20;
A=1'b1; B=1'b0; C=1'b0; D=1'b0; #20;
A=1'b1; B=1'b0; C=1'b0; D=1'b1; #20;
A=1'b1; B=1'b0; C=1'b1; D=1'b0; #20;
A=1'b1; B=1'b0; C=1'b1; D=1'b1; #20;
A=1'b1; B=1'b1; C=1'b0; D=1'b0; #20;
A=1'b1; B=1'b1; C=1'b0; D=1'b1; #20;
A=1'b1; B=1'b1; C=1'b1; D=1'b0; #20;
A=1'b1; B=1'b1; C=1'b1; D=1'b1; #20;

$display("Test Complete");

end

endmodule

SEM 3/DSDL/LAB2/Q2/Q2A/q2a_tb.vcd
$date
	Thu Sep  1 10:17:42 2022
$end
$version
	Icarus Verilog
$end
$timescale
	1ns
$end
$scope module q2a_tb $end
$var wire 1 ! f $end
$var reg 1 " A $end
$var reg 1 # B $end
$var reg 1 $ C $end
$var reg 1 % D $end
$scope module q2a $end
$var wire 1 " A $end
$var wire 1 # B $end
$var wire 1 $ C $end
$var wire 1 % D $end
$var wire 1 ! f $end
$upscope $end
$upscope $end
$enddefinitions $end
#0
$dumpvars
0%
0$
0#
0"
0!
$end
#20
1%
#40
1!
0%
1$
#60
1%
#80
0!
0%
0$
1#
#100
1!
1%
#120
0!
0%
1$
#140
1!
1%
#160
0!
0%
0$
0#
1"
#180
1%
#200
1!
0%
1$
#220
1%
#240
0!
0%
0$
1#
#260
1!
1%
#280
0!
0%
1$
#300
1!
1%
