SEM 3/DSDL/LAB6/Q2/q.v
module sixteentoone(i,s,f);
input [15:0]i;
input [3:0]s;
output f;
wire [3:0]c;
fourtoone f0(i[3:0],s[1:0],c[0]);
fourtoone f1(i[7:4],s[1:0],c[1]);
fourtoone f2(i[11:8],s[1:0],c[2]);
fourtoone f3(i[15:12],s[1:0],c[3]);
fourtoone f4(c[3:0],s[3:2],f);
endmodule

module fourtoone(i,s,f);
input [3:0]i;
input [1:0]s;
output f;
reg f;
always @(i,s)
begin
f = s[1]?(s[0]?i[3]:i[2]):(s[0]?i[1]:i[0]);
end
endmodule

SEM 3/DSDL/LAB6/Q3/q_tb.v
`timescale 1ns/1ns
`include "q.v"
module q_tb();
reg [15:0]i;
reg [3:0]s;
wire f;

sixteentoone f6(i,s,f);
initial
begin
$dumpfile("q_tb.vcd");
$dumpvars(0,q_tb);

i='hAAAA;
s=4'd0; #20;
s=4'd1; #20;
s=4'd2; #20;
s=4'd3; #20;
s=4'd4; #20;
s=4'd5; #20;
s=4'd6; #20;
s=4'd7; #20;
s=4'd8; #20;
s=4'd9; #20;
s=4'd10; #20;
s=4'd11; #20;
s=4'd12; #20;
s=4'd13; #20;
s=4'd14; #20;
s=4'd15; #20;



$display("Test Complete");
end
endmodule

SEM 3/DSDL/LAB6/Q2/q_tb.vcd
$date
	Thu Oct  6 10:20:33 2022
$end
$version
	Icarus Verilog
$end
$timescale
	1ns
$end
$scope module q_tb $end
$var wire 1 ! f $end
$var reg 16 " i [15:0] $end
$var reg 4 # s [3:0] $end
$scope module f6 $end
$var wire 16 $ i [15:0] $end
$var wire 4 % s [3:0] $end
$var wire 1 ! f $end
$var wire 4 & c [3:0] $end
$scope module f0 $end
$var wire 4 ' i [3:0] $end
$var wire 2 ( s [1:0] $end
$var reg 1 ) f $end
$upscope $end
$scope module f1 $end
$var wire 4 * i [3:0] $end
$var wire 2 + s [1:0] $end
$var reg 1 , f $end
$upscope $end
$scope module f2 $end
$var wire 4 - i [3:0] $end
$var wire 2 . s [1:0] $end
$var reg 1 / f $end
$upscope $end
$scope module f3 $end
$var wire 4 0 i [3:0] $end
$var wire 2 1 s [1:0] $end
$var reg 1 2 f $end
$upscope $end
$scope module f4 $end
$var wire 4 3 i [3:0] $end
$var wire 2 4 s [1:0] $end
$var reg 1 ! f $end
$upscope $end
$upscope $end
$upscope $end
$enddefinitions $end
#0
$dumpvars
b0 4
b0 3
02
b0 1
b1010 0
0/
b0 .
b1010 -
0,
b0 +
b1010 *
0)
b0 (
b1010 '
b0 &
b0 %
b1010101010101010 $
b0 #
b1010101010101010 "
0!
$end
#20
1!
1)
1,
1/
b1111 &
b1111 3
12
b1 (
b1 +
b1 .
b1 1
b1 #
b1 %
#40
0!
0)
0,
0/
b0 &
b0 3
02
b10 (
b10 +
b10 .
b10 1
b10 #
b10 %
#60
1!
1)
1,
1/
b1111 &
b1111 3
12
b11 (
b11 +
b11 .
b11 1
b11 #
b11 %
#80
0!
0)
0,
0/
b0 &
b0 3
02
b0 (
b0 +
b0 .
b0 1
b1 4
b100 #
b100 %
#100
1!
1)
1,
1/
b1111 &
b1111 3
12
b1 (
b1 +
b1 .
b1 1
b101 #
b101 %
#120
0!
0)
0,
0/
b0 &
b0 3
02
b10 (
b10 +
b10 .
b10 1
b110 #
b110 %
#140
1!
1)
1,
1/
b1111 &
b1111 3
12
b11 (
b11 +
b11 .
b11 1
b111 #
b111 %
#160
0!
0)
0,
0/
b0 &
b0 3
02
b0 (
b0 +
b0 .
b0 1
b10 4
b1000 #
b1000 %
#180
1!
1)
1,
1/
b1111 &
b1111 3
12
b1 (
b1 +
b1 .
b1 1
b1001 #
b1001 %
#200
0!
0)
0,
0/
b0 &
b0 3
02
b10 (
b10 +
b10 .
b10 1
b1010 #
b1010 %
#220
1!
1)
1,
1/
b1111 &
b1111 3
12
b11 (
b11 +
b11 .
b11 1
b1011 #
b1011 %
#240
0!
0)
0,
0/
b0 &
b0 3
02
b0 (
b0 +
b0 .
b0 1
b11 4
b1100 #
b1100 %
#260
1!
1)
1,
1/
b1111 &
b1111 3
12
b1 (
b1 +
b1 .
b1 1
b1101 #
b1101 %
#280
0!
0)
0,
0/
b0 &
b0 3
02
b10 (
b10 +
b10 .
b10 1
b1110 #
b1110 %
#300
1!
1)
1,
1/
b1111 &
b1111 3
12
b11 (
b11 +
b11 .
b11 1
b1111 #
b1111 %
