SEM 3/DSDL/LAB1/ADDITIONAL/ad1.v
module ad1(a,b,c,f1);
input a,b,c;
output f1;
assign f1=(a&~(c))|(b&c)|(~(b)&~(c));
endmodule

SEM 3/DSDL/LAB1/ADDITIONAL/ad1_tb.v
`timescale 1ns/1ns
`include "ad1.v"
//Name of the Verilog file
module ad1_tb();
reg a, b, c;
//Input
wire f1;
//Output
ad1 ad1(a, b, c, f1); //Instantiation of the module
initial
begin
$dumpfile("ad1_tb.vcd");
$dumpvars(0, ad1_tb);
a=1'b0; b=1'b0; c=1'b0;
#20;
a=1'b0; b=1'b0; c=1'b1;
#20;
a=1'b0; b=1'b1; c=1'b0;
#20;
a=1'b0; b=1'b1; c=1'b1;
#20;
a=1'b1; b=1'b0; c=1'b0;
#20;
a=1'b1; b=1'b0; c=1'b1;
#20;
a=1'b1; b=1'b1; c=1'b0;
#20;
a=1'b1; b=1'b1; c=1'b1;
#20;
$display("Test complete");
end
endmodule

SEM 3/DSDL/LAB1/ADDITIONAL/ad1_tb.vcd
$date
	Thu Aug 18 10:42:40 2022
$end
$version
	Icarus Verilog
$end
$timescale
	1ns
$end
$scope module ad1_tb $end
$var wire 1 ! f1 $end
$var reg 1 " a $end
$var reg 1 # b $end
$var reg 1 $ c $end
$scope module ad1 $end
$var wire 1 " a $end
$var wire 1 # b $end
$var wire 1 $ c $end
$var wire 1 ! f1 $end
$upscope $end
$upscope $end
$enddefinitions $end
#0
$dumpvars
0$
0#
0"
1!
$end
#20
0!
1$
#40
0$
1#
#60
1!
1$
#80
0$
0#
1"
#100
0!
1$
#120
1!
0$
1#
#140
1$
