SEM 3/DSDL/LAB1/ADDITIONAL/ad2.v
module ad2(a,b,c,f2);
input a,b,c;
output f2;

assign f2=(a|~b|c)&(a|b|~c)&(~a|b|~c);

endmodule

SEM 3/DSDL/LAB1/ADDITIONAL/ad2_tb.v
`timescale 1ns/1ns
`include "ad2.v"
//Name of the Verilog file
module ad2_tb();
reg a, b, c;
//Input
wire f2;
//Output
ad2 ad2(a, b, c, f2); //Instantiation of the module
initial
begin
$dumpfile("ad2_tb.vcd");
$dumpvars(0, ad2_tb);
a=1'b0; b=1'b0; c=1'b0;
#20;
a=1'b0; b=1'b0; c=1'b1;
#20;
a=1'b0; b=1'b1; c=1'b0;
#20;
a=1'b0; b=1'b1; c=1'b1;
#20;
a=1'b1; b=1'b0; c=1'b0;
#20;
a=1'b1; b=1'b0; c=1'b1;
#20;
a=1'b1; b=1'b1; c=1'b0;
#20;
a=1'b1; b=1'b1; c=1'b1;
#20;
$display("Test complete");
end
endmodule

SEM 3/DSDL/LAB1/ADDITIONAL/ad2_tb.vcd
$date
	Thu Aug 18 10:47:35 2022
$end
$version
	Icarus Verilog
$end
$timescale
	1ns
$end
$scope module ad2_tb $end
$var wire 1 ! f2 $end
$var reg 1 " a $end
$var reg 1 # b $end
$var reg 1 $ c $end
$scope module ad2 $end
$var wire 1 " a $end
$var wire 1 # b $end
$var wire 1 $ c $end
$var wire 1 ! f2 $end
$upscope $end
$upscope $end
$enddefinitions $end
#0
$dumpvars
0$
0#
0"
1!
$end
#20
0!
1$
#40
0!
0$
1#
#60
1!
1$
#80
0$
0#
1"
#100
0!
1$
#120
1!
0$
1#
#140
1$
