SEM 3/DSDL/LAB3/Q4/q4.v
module q4(A,B,C,D,f);
input A,B,C,D;
output f;
assign f=~(~(~(A|A)|~(C|C))|~(D|D));
endmodule

SEM 3/DSDL/LAB3/Q4/q4_tb.v
`timescale 1ns/1ns
`include "q4.v"
module q4_tb();
reg A,B,C,D;
wire f;
q4 q4(A,B,C,D,f);
initial
begin
$dumpfile("q4_tb.vcd");
$dumpvars(0,q4_tb);

A=1'b0; B=1'b0; C=1'b0; D=1'b0; #20;
A=1'b0; B=1'b0; C=1'b0; D=1'b1; #20;
A=1'b0; B=1'b0; C=1'b1; D=1'b0; #20;
A=1'b0; B=1'b0; C=1'b1; D=1'b1; #20;
A=1'b0; B=1'b1; C=1'b0; D=1'b0; #20;
A=1'b0; B=1'b1; C=1'b0; D=1'b1; #20;
A=1'b0; B=1'b1; C=1'b1; D=1'b0; #20;
A=1'b0; B=1'b1; C=1'b1; D=1'b1; #20;
A=1'b1; B=1'b0; C=1'b0; D=1'b0; #20;
A=1'b1; B=1'b0; C=1'b0; D=1'b1; #20;
A=1'b1; B=1'b0; C=1'b1; D=1'b0; #20;
A=1'b1; B=1'b0; C=1'b1; D=1'b1; #20;
A=1'b1; B=1'b1; C=1'b0; D=1'b0; #20;
A=1'b1; B=1'b1; C=1'b0; D=1'b1; #20;
A=1'b1; B=1'b1; C=1'b1; D=1'b0; #20;
A=1'b1; B=1'b1; C=1'b1; D=1'b1; #20;

$display("Test Complete");
end
endmodule

SEM 3/DSDL/LAB3/Q4/q4_tb.vcd
$date
	Wed Sep 14 14:17:29 2022
$end
$version
	Icarus Verilog
$end
$timescale
	1ns
$end
$scope module q4_tb $end
$var wire 1 ! f $end
$var reg 1 " A $end
$var reg 1 # B $end
$var reg 1 $ C $end
$var reg 1 % D $end
$scope module q4 $end
$var wire 1 " A $end
$var wire 1 # B $end
$var wire 1 $ C $end
$var wire 1 % D $end
$var wire 1 ! f $end
$upscope $end
$upscope $end
$enddefinitions $end
$comment Show the parameter values. $end
$dumpall
$end
#0
$dumpvars
0%
0$
0#
0"
0!
$end
#20
1!
1%
#40
0!
0%
1$
#60
1!
1%
#80
0!
0%
0$
1#
#100
1!
1%
#120
0!
0%
1$
#140
1!
1%
#160
0!
0%
0$
0#
1"
#180
1!
1%
#200
0!
0%
1$
#220
1%
#240
0%
0$
1#
#260
1!
1%
#280
0!
0%
1$
#300
1%
