SEM 3/DSDL/LAB3/Q2/q2.v
module q2(A,B,C,D,f);
input A,B,C,D;
output f;
assign g=~(~(A|C|~(D|D))|~(B|C)|~(B|D));
assign f=~(g|g);
endmodule

SEM 3/DSDL/LAB3/Q2/q2_tb.v
`timescale 1ns/1ns
`include "q2.v"
module q2_tb();
reg A,B,C,D;
wire f;
q2 q2(A,B,C,D,f);
initial
begin
$dumpfile("q2_tb.vcd");
$dumpvars(0,q2_tb);

A=1'b0; B=1'b0; C=1'b0; D=1'b0; #20;
A=1'b0; B=1'b0; C=1'b0; D=1'b1; #20;
A=1'b0; B=1'b0; C=1'b1; D=1'b0; #20;
A=1'b0; B=1'b0; C=1'b1; D=1'b1; #20;
A=1'b0; B=1'b1; C=1'b0; D=1'b0; #20;
A=1'b0; B=1'b1; C=1'b0; D=1'b1; #20;
A=1'b0; B=1'b1; C=1'b1; D=1'b0; #20;
A=1'b0; B=1'b1; C=1'b1; D=1'b1; #20;
A=1'b1; B=1'b0; C=1'b0; D=1'b0; #20;
A=1'b1; B=1'b0; C=1'b0; D=1'b1; #20;
A=1'b1; B=1'b0; C=1'b1; D=1'b0; #20;
A=1'b1; B=1'b0; C=1'b1; D=1'b1; #20;
A=1'b1; B=1'b1; C=1'b0; D=1'b0; #20;
A=1'b1; B=1'b1; C=1'b0; D=1'b1; #20;
A=1'b1; B=1'b1; C=1'b1; D=1'b0; #20;
A=1'b1; B=1'b1; C=1'b1; D=1'b1; #20;

$display("Test Complete");
end
endmodule

SEM 3/DSDL/LAB3/Q2/q2_tb.vcd
$date
	Thu Sep  8 09:38:16 2022
$end
$version
	Icarus Verilog
$end
$timescale
	1ns
$end
$scope module q2_tb $end
$var wire 1 ! f $end
$var reg 1 " A $end
$var reg 1 # B $end
$var reg 1 $ C $end
$var reg 1 % D $end
$scope module q2 $end
$var wire 1 " A $end
$var wire 1 # B $end
$var wire 1 $ C $end
$var wire 1 % D $end
$var wire 1 ! f $end
$var wire 1 & g $end
$upscope $end
$upscope $end
$enddefinitions $end
#0
$dumpvars
0&
0%
0$
0#
0"
1!
$end
#20
1%
#40
0%
1$
#60
0!
1&
1%
#80
0!
1&
0%
0$
1#
#100
1!
0&
1%
#120
0!
1&
0%
1$
#140
1%
#160
1!
0&
0%
0$
0#
1"
#180
1%
#200
0%
1$
#220
0!
1&
1%
#240
0%
0$
1#
#260
1%
#280
0%
1$
#300
1%
