SEM 3/DSDL/LAB4/Q1/qb.v
module halfadder(x,y,sum,cout);
input x,y;
output sum,cout;
assign sum=x^y;
assign cout=x&y;
endmodule

module fulladder(x1,y1,Cin,Sum,Cout);
input x1,y1,Cin;
output Sum,Cout;
assign Sum=x1^y1^Cin;
assign Cout = (x1&y1)|(x1&Cin)|(y1&Cin);
endmodule

module decomposedfulladder(x2,y2,CIn,Sum1,Cout1);
input x2,y2,CIn;
output Sum1,Cout1;
halfadder stage0(x2,y2,s1,c1);
halfadder stage1(s1,CIn,Sum1,c2);
assign Cout1 = c1|c2;
endmodule

SEM 3/DSDL/LAB4/Q1/qb_tb.v
`timescale 1ns/1ns
`include "qb.v"
module qb_tb();
reg x,y;
wire sum,cout;
halfadder ha(x,y,sum,cout);
initial
begin
$dumpfile("qb_tb.vcd");
$dumpvars(0,qb_tb);

x=1'b0; y=1'b0; #20;
x=1'b0; y=1'b1; #20;
x=1'b1; y=1'b0; #20;
x=1'b1; y=1'b1; #20; 

$display("Test Complete");
end

reg x1,y1,Cin;
wire Sum,Cout;
fulladder fa(x1,y1,Cin,Sum,Cout);
initial
begin
$dumpfile("qb_tb.vcd");
$dumpvars(0,qb_tb);

x1=1'b0; y1=1'b0; Cin=1'b0; #20;
x1=1'b0; y1=1'b0; Cin=1'b1; #20;
x1=1'b0; y1=1'b1; Cin=1'b0; #20;
x1=1'b0; y1=1'b1; Cin=1'b1; #20;
x1=1'b1; y1=1'b0; Cin=1'b0; #20;
x1=1'b1; y1=1'b0; Cin=1'b1; #20;
x1=1'b1; y1=1'b1; Cin=1'b0; #20;
x1=1'b1; y1=1'b1; Cin=1'b1; #20;

$display("Test Complete");
end

reg x2,y2,CIn;
wire Sum1,Cout1;
decomposedfulladder dfa(x2,y2,CIn,Sum1,Cout1);
initial
begin
$dumpfile("qb_tb.vcd");
$dumpvars(0,qb_tb);

x2=1'b0; y2=1'b0; CIn=1'b0; #20;
x2=1'b0; y2=1'b0; CIn=1'b1; #20;
x2=1'b0; y2=1'b1; CIn=1'b0; #20;
x2=1'b0; y2=1'b1; CIn=1'b1; #20;
x2=1'b1; y2=1'b0; CIn=1'b0; #20;
x2=1'b1; y2=1'b0; CIn=1'b1; #20;
x2=1'b1; y2=1'b1; CIn=1'b0; #20;
x2=1'b1; y2=1'b1; CIn=1'b1; #20;

$display("Test Complete");
end
endmodule

SEM 3/DSDL/LAB4/Q1/qb_tb.vcd
$date
	Thu Sep 15 09:37:37 2022
$end
$version
	Icarus Verilog
$end
$timescale
	1ns
$end
$scope module qb_tb $end
$var wire 1 ! sum $end
$var wire 1 " cout $end
$var wire 1 # Sum1 $end
$var wire 1 $ Sum $end
$var wire 1 % Cout1 $end
$var wire 1 & Cout $end
$var reg 1 ' CIn $end
$var reg 1 ( Cin $end
$var reg 1 ) x $end
$var reg 1 * x1 $end
$var reg 1 + x2 $end
$var reg 1 , y $end
$var reg 1 - y1 $end
$var reg 1 . y2 $end
$scope module dfa $end
$var wire 1 ' CIn $end
$var wire 1 % Cout1 $end
$var wire 1 + x2 $end
$var wire 1 . y2 $end
$var wire 1 / s1 $end
$var wire 1 0 c2 $end
$var wire 1 1 c1 $end
$var wire 1 # Sum1 $end
$scope module stage0 $end
$var wire 1 1 cout $end
$var wire 1 / sum $end
$var wire 1 + x $end
$var wire 1 . y $end
$upscope $end
$scope module stage1 $end
$var wire 1 0 cout $end
$var wire 1 # sum $end
$var wire 1 / x $end
$var wire 1 ' y $end
$upscope $end
$upscope $end
$scope module fa $end
$var wire 1 ( Cin $end
$var wire 1 & Cout $end
$var wire 1 $ Sum $end
$var wire 1 * x1 $end
$var wire 1 - y1 $end
$upscope $end
$scope module ha $end
$var wire 1 " cout $end
$var wire 1 ! sum $end
$var wire 1 ) x $end
$var wire 1 , y $end
$upscope $end
$upscope $end
$scope module qb_tb $end
$scope module dfa $end
$scope module stage0 $end
$upscope $end
$scope module stage1 $end
$upscope $end
$upscope $end
$scope module fa $end
$upscope $end
$scope module ha $end
$upscope $end
$upscope $end
$scope module qb_tb $end
$scope module dfa $end
$scope module stage0 $end
$upscope $end
$scope module stage1 $end
$upscope $end
$upscope $end
$scope module fa $end
$upscope $end
$scope module ha $end
$upscope $end
$upscope $end
$enddefinitions $end
#0
$dumpvars
01
00
0/
0.
0-
0,
0+
0*
0)
0(
0'
0&
0%
0$
0#
0"
0!
$end
#20
1#
1$
1!
1'
1(
1,
#40
1/
0'
1.
0(
1-
0,
1)
#60
1%
1&
0#
10
0$
0!
1"
1'
1(
1,
#80
0%
0&
1#
00
1$
0'
0.
1+
0(
0-
1*
#100
1&
1%
0#
10
0$
1'
1(
#120
00
0/
11
0'
1.
0(
1-
#140
1#
1$
1'
1(
