SEM 3/DSDL/LAB2/Q3/q3.v
module q3(x1,x2,x3,x4,f);
input x1,x2,x3,x4;
output f;
assign f=(x2&x3&x4)|(x1&x2&x3)|(x1&x3&x4)|(x1&x2&x4);
endmodule

SEM 3/DSDL/LAB2/Q3/q3_tb.v
`timescale 1ns/1ns
`include "q3.v"

module q3_tb();
reg x1,x2,x3,x4;
wire f;

q3 q3(x1,x2,x3,x4,f);
initial
begin

$dumpfile("q3_tb.vcd");
$dumpvars(0,q3_tb);

x1=1'b0; x2=1'b0; x3=1'b0; x4=1'b0; #20;
x1=1'b0; x2=1'b0; x3=1'b0; x4=1'b1; #20;
x1=1'b0; x2=1'b0; x3=1'b1; x4=1'b0; #20;
x1=1'b0; x2=1'b0; x3=1'b1; x4=1'b1; #20;
x1=1'b0; x2=1'b1; x3=1'b0; x4=1'b0; #20;
x1=1'b0; x2=1'b1; x3=1'b0; x4=1'b1; #20;
x1=1'b0; x2=1'b1; x3=1'b1; x4=1'b0; #20;
x1=1'b0; x2=1'b1; x3=1'b1; x4=1'b1; #20;
x1=1'b1; x2=1'b0; x3=1'b0; x4=1'b0; #20;
x1=1'b1; x2=1'b0; x3=1'b0; x4=1'b1; #20;
x1=1'b1; x2=1'b0; x3=1'b1; x4=1'b0; #20;
x1=1'b1; x2=1'b0; x3=1'b1; x4=1'b1; #20;
x1=1'b1; x2=1'b1; x3=1'b0; x4=1'b0; #20;
x1=1'b1; x2=1'b1; x3=1'b0; x4=1'b1; #20;
x1=1'b1; x2=1'b1; x3=1'b1; x4=1'b0; #20;
x1=1'b1; x2=1'b1; x3=1'b1; x4=1'b1; #20;

$display("Test Complete");

end

endmodule

SEM 3/DSDL/LAB2/Q3/q3_tb.vcd
$date
	Thu Sep  1 11:02:38 2022
$end
$version
	Icarus Verilog
$end
$timescale
	1ns
$end
$scope module q3_tb $end
$var wire 1 ! f $end
$var reg 1 " x1 $end
$var reg 1 # x2 $end
$var reg 1 $ x3 $end
$var reg 1 % x4 $end
$scope module q3 $end
$var wire 1 ! f $end
$var wire 1 " x1 $end
$var wire 1 # x2 $end
$var wire 1 $ x3 $end
$var wire 1 % x4 $end
$upscope $end
$upscope $end
$enddefinitions $end
#0
$dumpvars
0%
0$
0#
0"
0!
$end
#20
1%
#40
0%
1$
#60
1%
#80
0%
0$
1#
#100
1%
#120
0%
1$
#140
1!
1%
#160
0!
0%
0$
0#
1"
#180
1%
#200
0%
1$
#220
1!
1%
#240
0!
0%
0$
1#
#260
1!
1%
#280
1!
0%
1$
#300
1%
