SEM 3/DSDL/LAB9/Q2/q.v
module q(i,f,g,h,En);
input [3:0]i;
input En;
output f,g,h;
wire [15:0]c;
fourtosixteen s0(i,c,En);
assign f = c[11]|c[10]|c[7]|c[3]|c[14]|c[6];
assign g = c[14]|c[10]|c[2]|c[3];
assign h = c[1]|c[0]|c[14]|c[15]|c[7]|c[3];

endmodule

module fourtosixteen(i,f,En);
input [3:0]i;
input En;
output [15:0]f;
wire [3:0]c;
twotofour stage0(i[3:2],c[3:0],En);
twotofour stage1(i[1:0],f[3:0],c[0]);
twotofour stage2(i[1:0],f[7:4],c[1]);
twotofour stage3(i[1:0],f[11:8],c[2]);
twotofour stage4(i[1:0],f[15:12],c[3]);
endmodule

module twotofour(i,f,En);
input [1:0]i;
input En;
output reg [3:0]f;
always @ (i,En)
begin

case(En)
0:f=4'd0;
1:
begin
	case(i)
	0:f=4'd1;
	1:f=4'd2;
	2:f=4'd4;
	3:f=4'd8;
	endcase
end
endcase
end
endmodule

SEM 3/DSDL/LAB9/Q2/q_tb.v
`timescale 1ns/1ns
`include "q.v"
module q_tb();
reg [3:0]i;
reg En;
wire f,g,h;
integer j;
q f1(i,f,g,h,En);
initial
begin
$dumpfile("q_tb.vcd");
$dumpvars(0,q_tb);
En=1'b1;
for(j=0;j<16;j=j+1)
begin
i=j; #20;
end
$display("Test Complete");
end
endmodule

SEM 3/DSDL/LAB9/Q2/q_tb.vcd
$date
	Thu Oct 27 11:10:12 2022
$end
$version
	Icarus Verilog
$end
$timescale
	1ns
$end
$scope module q_tb $end
$var wire 1 ! h $end
$var wire 1 " g $end
$var wire 1 # f $end
$var reg 1 $ En $end
$var reg 4 % i [3:0] $end
$var integer 32 & j [31:0] $end
$scope module f1 $end
$var wire 1 $ En $end
$var wire 1 # f $end
$var wire 1 " g $end
$var wire 1 ! h $end
$var wire 4 ' i [3:0] $end
$var wire 16 ( c [15:0] $end
$scope module s0 $end
$var wire 1 $ En $end
$var wire 4 ) i [3:0] $end
$var wire 16 * f [15:0] $end
$var wire 4 + c [3:0] $end
$scope module stage0 $end
$var wire 1 $ En $end
$var wire 2 , i [1:0] $end
$var reg 4 - f [3:0] $end
$upscope $end
$scope module stage1 $end
$var wire 1 . En $end
$var wire 2 / i [1:0] $end
$var reg 4 0 f [3:0] $end
$upscope $end
$scope module stage2 $end
$var wire 1 1 En $end
$var wire 2 2 i [1:0] $end
$var reg 4 3 f [3:0] $end
$upscope $end
$scope module stage3 $end
$var wire 1 4 En $end
$var wire 2 5 i [1:0] $end
$var reg 4 6 f [3:0] $end
$upscope $end
$scope module stage4 $end
$var wire 1 7 En $end
$var wire 2 8 i [1:0] $end
$var reg 4 9 f [3:0] $end
$upscope $end
$upscope $end
$upscope $end
$upscope $end
$enddefinitions $end
#0
$dumpvars
b0 9
b0 8
07
b0 6
b0 5
04
b0 3
b0 2
01
b1 0
b0 /
1.
b1 -
b0 ,
b1 +
b1 *
b0 )
b1 (
b0 '
b0 &
b0 %
1$
0#
0"
1!
$end
#20
b10 (
b10 *
b10 0
b1 /
b1 2
b1 5
b1 8
b1 %
b1 '
b1 )
b1 &
#40
0!
1"
b100 (
b100 *
b100 0
b10 /
b10 2
b10 5
b10 8
b10 %
b10 '
b10 )
b10 &
#60
1#
1!
b1000 (
b1000 *
b1000 0
b11 /
b11 2
b11 5
b11 8
b11 %
b11 '
b11 )
b11 &
#80
0#
b1 3
0!
0"
11
0.
b10 +
b10 -
b10000 (
b10000 *
b0 0
b1 ,
b0 /
b0 2
b0 5
b0 8
b100 %
b100 '
b100 )
b100 &
#100
b100000 (
b100000 *
b10 3
b1 /
b1 2
b1 5
b1 8
b101 %
b101 '
b101 )
b101 &
#120
1#
b1000000 (
b1000000 *
b100 3
b10 /
b10 2
b10 5
b10 8
b110 %
b110 '
b110 )
b110 &
#140
1!
1#
b10000000 (
b10000000 *
b1000 3
b11 /
b11 2
b11 5
b11 8
b111 %
b111 '
b111 )
b111 &
#160
0#
0!
b1 6
14
01
b100 +
b100 -
b100000000 (
b100000000 *
b0 3
b10 ,
b0 /
b0 2
b0 5
b0 8
b1000 %
b1000 '
b1000 )
b1000 &
#180
b1000000000 (
b1000000000 *
b10 6
b1 /
b1 2
b1 5
b1 8
b1001 %
b1001 '
b1001 )
b1001 &
#200
1#
1"
b10000000000 (
b10000000000 *
b100 6
b10 /
b10 2
b10 5
b10 8
b1010 %
b1010 '
b1010 )
b1010 &
#220
0"
b100000000000 (
b100000000000 *
b1000 6
b11 /
b11 2
b11 5
b11 8
b1011 %
b1011 '
b1011 )
b1011 &
#240
0#
b1 9
17
04
b1000 +
b1000 -
b1000000000000 (
b1000000000000 *
b0 6
b11 ,
b0 /
b0 2
b0 5
b0 8
b1100 %
b1100 '
b1100 )
b1100 &
#260
b10000000000000 (
b10000000000000 *
b10 9
b1 /
b1 2
b1 5
b1 8
b1101 %
b1101 '
b1101 )
b1101 &
#280
1!
1"
1#
b100000000000000 (
b100000000000000 *
b100 9
b10 /
b10 2
b10 5
b10 8
b1110 %
b1110 '
b1110 )
b1110 &
#300
0"
0#
b1000000000000000 (
b1000000000000000 *
b1000 9
b11 /
b11 2
b11 5
b11 8
b1111 %
b1111 '
b1111 )
b1111 &
#320
b10000 &
