SEM 3/DSDL/LAB8/Q3/q.v
module fourtosixteen(i,f,En);
input [3:0]i;
input En;
output [15:0]f;
wire [3:0]c;
twotofour stage0(i[3:2],c[3:0],En);
twotofour stage1(i[1:0],f[3:0],~c[0]);
twotofour stage2(i[1:0],f[7:4],~c[1]);
twotofour stage3(i[1:0],f[11:8],~c[2]);
twotofour stage4(i[1:0],f[15:12],~c[3]);
endmodule

module twotofour(i,f,En);
input [1:0]i;
input En;
output reg [3:0]f;
always @ (i,En)
begin

case(En)
0:f=4'b1111;
1:
begin
	case(i)
	0:f=4'b1110;
	1:f=4'b1101;
	2:f=4'b1011;
	3:f=4'b0111;
	endcase
end
endcase
end
endmodule

SEM 3/DSDL/LAB8/Q3/q_tb.v
`timescale 1ns/1ns
`include "q.v"
module q_tb();
reg [3:0]i;
reg En;
wire [15:0]f;
integer j;
fourtosixteen f1(i,f,En);
initial
begin
$dumpfile("q_tb.vcd");
$dumpvars(0,q_tb);
En=1'b1;
for(j=0;j<16;j=j+1)
begin
i=j; #20;
end
$display("Test Complete");
end
endmodule

SEM 3/DSDL/LAB8/Q3/q_tb.vcd
$date
	Thu Oct 20 10:37:00 2022
$end
$version
	Icarus Verilog
$end
$timescale
	1ns
$end
$scope module q_tb $end
$var wire 16 ! f [15:0] $end
$var reg 1 " En $end
$var reg 4 # i [3:0] $end
$var integer 32 $ j [31:0] $end
$scope module f1 $end
$var wire 1 " En $end
$var wire 4 % i [3:0] $end
$var wire 16 & f [15:0] $end
$var wire 4 ' c [3:0] $end
$scope module stage0 $end
$var wire 1 " En $end
$var wire 2 ( i [1:0] $end
$var reg 4 ) f [3:0] $end
$upscope $end
$scope module stage1 $end
$var wire 1 * En $end
$var wire 2 + i [1:0] $end
$var reg 4 , f [3:0] $end
$upscope $end
$scope module stage2 $end
$var wire 1 - En $end
$var wire 2 . i [1:0] $end
$var reg 4 / f [3:0] $end
$upscope $end
$scope module stage3 $end
$var wire 1 0 En $end
$var wire 2 1 i [1:0] $end
$var reg 4 2 f [3:0] $end
$upscope $end
$scope module stage4 $end
$var wire 1 3 En $end
$var wire 2 4 i [1:0] $end
$var reg 4 5 f [3:0] $end
$upscope $end
$upscope $end
$upscope $end
$enddefinitions $end
#0
$dumpvars
b1111 5
b0 4
03
b1111 2
b0 1
00
b1111 /
b0 .
0-
b1110 ,
b0 +
1*
b1110 )
b0 (
b1110 '
b1111111111111110 &
b0 %
b0 $
b0 #
1"
b1111111111111110 !
$end
#20
b1111111111111101 !
b1111111111111101 &
b1101 ,
b1 +
b1 .
b1 1
b1 4
b1 #
b1 %
b1 $
#40
b1111111111111011 !
b1111111111111011 &
b1011 ,
b10 +
b10 .
b10 1
b10 4
b10 #
b10 %
b10 $
#60
b1111111111110111 !
b1111111111110111 &
b111 ,
b11 +
b11 .
b11 1
b11 4
b11 #
b11 %
b11 $
#80
b1110 /
1-
0*
b1101 '
b1101 )
b1111111111101111 !
b1111111111101111 &
b1111 ,
b1 (
b0 +
b0 .
b0 1
b0 4
b100 #
b100 %
b100 $
#100
b1111111111011111 !
b1111111111011111 &
b1101 /
b1 +
b1 .
b1 1
b1 4
b101 #
b101 %
b101 $
#120
b1111111110111111 !
b1111111110111111 &
b1011 /
b10 +
b10 .
b10 1
b10 4
b110 #
b110 %
b110 $
#140
b1111111101111111 !
b1111111101111111 &
b111 /
b11 +
b11 .
b11 1
b11 4
b111 #
b111 %
b111 $
#160
b1110 2
10
0-
b1011 '
b1011 )
b1111111011111111 !
b1111111011111111 &
b1111 /
b10 (
b0 +
b0 .
b0 1
b0 4
b1000 #
b1000 %
b1000 $
#180
b1111110111111111 !
b1111110111111111 &
b1101 2
b1 +
b1 .
b1 1
b1 4
b1001 #
b1001 %
b1001 $
#200
b1111101111111111 !
b1111101111111111 &
b1011 2
b10 +
b10 .
b10 1
b10 4
b1010 #
b1010 %
b1010 $
#220
b1111011111111111 !
b1111011111111111 &
b111 2
b11 +
b11 .
b11 1
b11 4
b1011 #
b1011 %
b1011 $
#240
b1110 5
13
00
b111 '
b111 )
b1110111111111111 !
b1110111111111111 &
b1111 2
b11 (
b0 +
b0 .
b0 1
b0 4
b1100 #
b1100 %
b1100 $
#260
b1101111111111111 !
b1101111111111111 &
b1101 5
b1 +
b1 .
b1 1
b1 4
b1101 #
b1101 %
b1101 $
#280
b1011111111111111 !
b1011111111111111 &
b1011 5
b10 +
b10 .
b10 1
b10 4
b1110 #
b1110 %
b1110 $
#300
b111111111111111 !
b111111111111111 &
b111 5
b11 +
b11 .
b11 1
b11 4
b1111 #
b1111 %
b1111 $
#320
b10000 $
