SEM 3/DSDL/LAB11/Q1/q.v
module rc(clock,set,Resetn,Q);
input set,clock,Resetn;
output [3:0]Q;
dff s0(Q[0],clock,set,Resetn,Q[3]);
dff s1(Q[3],clock,~set,Resetn,Q[2]);
dff s2(Q[2],clock,~set,Resetn,Q[1]);
dff s3(Q[1],clock,~set,Resetn,Q[0]);
endmodule

module dff(D,clock,set,Resetn,Q);
input D,set,clock,Resetn;
output reg Q;
always @ (posedge clock )
begin
if(!Resetn && set)
	Q <= 1;
else if(!Resetn)
	Q <= 0;
else
	Q <= D;
end
endmodule

SEM 3/DSDL/LAB11/Q1/q_tb.v
`timescale 1ns/1ns
`include "q.v"
module q_tb();
reg set,clock, Resetn;
wire[3:0] Q;
integer i;
rc f1(clock,set,Resetn, Q);

initial
begin
$dumpfile("q_tb.vcd");
$dumpvars(0, q_tb);
clock=0;
forever #20 clock = ~clock;
end

initial
begin
repeat ( 2 )
begin
Resetn=0; set=1; #40;
Resetn=1; set=0; #160;
end
#20;
$display("Test complete");
$finish;
end

endmodule

SEM 3/DSDL/LAB11/Q1/q_tb.vcd
$date
	Thu Nov 17 09:50:29 2022
$end
$version
	Icarus Verilog
$end
$timescale
	1ns
$end
$scope module q_tb $end
$var wire 4 ! Q [3:0] $end
$var reg 1 " Resetn $end
$var reg 1 # clock $end
$var reg 1 $ set $end
$scope module f1 $end
$var wire 1 " Resetn $end
$var wire 1 # clock $end
$var wire 1 $ set $end
$var wire 4 % Q [3:0] $end
$scope module s0 $end
$var wire 1 & D $end
$var wire 1 " Resetn $end
$var wire 1 # clock $end
$var wire 1 $ set $end
$var reg 1 ' Q $end
$upscope $end
$scope module s1 $end
$var wire 1 ( D $end
$var wire 1 " Resetn $end
$var wire 1 # clock $end
$var wire 1 ) set $end
$var reg 1 * Q $end
$upscope $end
$scope module s2 $end
$var wire 1 + D $end
$var wire 1 " Resetn $end
$var wire 1 # clock $end
$var wire 1 , set $end
$var reg 1 - Q $end
$upscope $end
$scope module s3 $end
$var wire 1 . D $end
$var wire 1 " Resetn $end
$var wire 1 # clock $end
$var wire 1 / set $end
$var reg 1 0 Q $end
$upscope $end
$upscope $end
$upscope $end
$enddefinitions $end
#0
$dumpvars
x0
0/
x.
x-
0,
x+
x*
0)
x(
x'
x&
bx %
1$
0#
0"
bx !
$end
#20
1(
0+
0.
0&
1'
0*
0-
b1000 !
b1000 %
00
1#
#40
1)
1,
1/
0#
0$
1"
#60
1+
0(
1*
b100 !
b100 %
0'
1#
#80
0#
#100
0+
1.
0*
b10 !
b10 %
1-
1#
#120
0#
#140
1&
0.
10
b1 !
b1 %
0-
1#
#160
0#
#180
1(
0&
1'
b1000 !
b1000 %
00
1#
#200
0)
0,
0/
0#
1$
0"
#220
1#
#240
1)
1,
1/
0#
0$
1"
#260
0(
1+
0'
b100 !
b100 %
1*
1#
#280
0#
#300
1.
0+
1-
b10 !
b10 %
0*
1#
#320
0#
#340
0.
1&
0-
b1 !
b1 %
10
1#
#360
0#
#380
0&
1(
00
b1000 !
b1000 %
1'
1#
#400
0#
#420
0(
1+
0'
b100 !
b100 %
1*
1#
