SEM 3/DSDL/LAB1/Q1/q1b.v
module q1b(a,b,c,d,f);
input a,b,c,d;
output f;
assign f=(((~((a&b)|c))&d)&(((a&b)|c)|d));
endmodule

SEM 3/DSDL/LAB1/Q1/q1b_tb.v
`timescale 1ns/1ns
`include "q1b.v"

module q1b_tb();
reg a,b,c,d;
wire f;

q1b q1b(a,b,c,d,f);
initial
begin

$dumpfile("q1b_tb.vcd");
$dumpvars(0,q1b_tb);

a=1'b0; b=1'b0; c=1'b0; d=1'b0; #20;
a=1'b0; b=1'b0; c=1'b0; d=1'b1; #20;
a=1'b0; b=1'b0; c=1'b1; d=1'b0; #20;
a=1'b0; b=1'b0; c=1'b1; d=1'b1; #20;
a=1'b0; b=1'b1; c=1'b0; d=1'b0; #20;
a=1'b0; b=1'b1; c=1'b0; d=1'b1; #20;
a=1'b0; b=1'b1; c=1'b1; d=1'b0; #20;
a=1'b0; b=1'b1; c=1'b1; d=1'b1; #20;
a=1'b1; b=1'b0; c=1'b0; d=1'b0; #20;
a=1'b1; b=1'b0; c=1'b0; d=1'b1; #20;
a=1'b1; b=1'b0; c=1'b1; d=1'b0; #20;
a=1'b1; b=1'b0; c=1'b1; d=1'b1; #20;
a=1'b1; b=1'b1; c=1'b0; d=1'b0; #20;
a=1'b1; b=1'b1; c=1'b0; d=1'b1; #20;
a=1'b1; b=1'b1; c=1'b1; d=1'b0; #20;
a=1'b1; b=1'b1; c=1'b1; d=1'b1; #20;

$display("Test Complete");

end

endmodule

SEM 3/DSDL/LAB1/Q1/q1b_tb.vcd
$date
	Thu Aug 18 11:02:50 2022
$end
$version
	Icarus Verilog
$end
$timescale
	1ns
$end
$scope module q1b_tb $end
$var wire 1 ! f $end
$var reg 1 " a $end
$var reg 1 # b $end
$var reg 1 $ c $end
$var reg 1 % d $end
$scope module q1b $end
$var wire 1 " a $end
$var wire 1 # b $end
$var wire 1 $ c $end
$var wire 1 % d $end
$var wire 1 ! f $end
$upscope $end
$upscope $end
$enddefinitions $end
#0
$dumpvars
0%
0$
0#
0"
0!
$end
#20
1!
1%
#40
0!
0%
1$
#60
1%
#80
0%
0$
1#
#100
1!
1%
#120
0!
0%
1$
#140
1%
#160
0%
0$
0#
1"
#180
1!
1%
#200
0!
0%
1$
#220
1%
#240
0%
0$
1#
#260
1%
#280
0%
1$
#300
1%
